tf_stitch/__init__.py
tf_stitch/__main__.py
tf_stitch/stitch.py
tf_stitch/stitch_ipynb.py
tf_stitch/template.json
tf_stitch/templates/dataset/dataset.py
tf_stitch/templates/imports/imports.py
tf_stitch/templates/model/conv_model.py
tf_stitch/templates/model/custom_model.py
tf_stitch/templates/model/dnn_model.py
tf_stitch/templates/model/recurrent_model.py
tf_stitch/templates/preprocessing/image.py
tf_stitch/templates/preprocessing/sequence.py
tf_stitch/templates/testing/testing.py
tf_stitch/templates/training/built_in_train.py
tf_stitch/templates/training/custom_train.py
tf_stitch-1.2.1.dist-info/LICENSE
tf_stitch-1.2.1.dist-info/METADATA
tf_stitch-1.2.1.dist-info/WHEEL
tf_stitch-1.2.1.dist-info/entry_points.txt
tf_stitch-1.2.1.dist-info/top_level.txt
tf_stitch-1.2.1.dist-info/RECORD
