Metadata-Version: 2.1
Name: tf-stitch
Version: 1.2.1
Summary: Quick Starter Code with different specifications stitched together in tensorflow 2.0 .
Home-page: https://github.com/amifunny/tf-stitch/
Author: Hemant Singh
Maintainer: amifunny
License: UNKNOWN
Keywords: Deep learning,tensorflow,tf2.0,keras,Boilerplate,Starter Code,Starter Pieces,Quick Work,Productivity
Platform: UNKNOWN
Classifier: Programming Language :: Python :: 3
Classifier: License :: OSI Approved :: MIT License
Classifier: Operating System :: OS Independent
